[{"year_month":"2025-05","usage_kwh":2541.278,"prev_year_usage_kwh":2712.125,"cost_won":617770,"prev_year_cost_won":661740},{"year_month":"2025-06","usage_kwh":3291.263,"prev_year_usage_kwh":3602.076,"cost_won":790790,"prev_year_cost_won":821350},{"year_month":"2025-07","usage_kwh":5480.06,"prev_year_usage_kwh":4192.996,"cost_won":1060760,"prev_year_cost_won":998880},{"year_month":"2025-08","usage_kwh":5182.12,"prev_year_usage_kwh":5277.383,"cost_won":1245320,"prev_year_cost_won":1147430},{"year_month":"2025-09","usage_kwh":3733.081,"prev_year_usage_kwh":3642.056,"cost_won":1020870,"prev_year_cost_won":986420},{"year_month":"2025-10","usage_kwh":2486.232,"prev_year_usage_kwh":2507.566,"cost_won":646060,"prev_year_cost_won":693170},{"year_month":"2025-11","usage_kwh":4009.226,"prev_year_usage_kwh":3513.102,"cost_won":799150,"prev_year_cost_won":695170},{"year_month":"2025-12","usage_kwh":7114.609,"prev_year_usage_kwh":7009.497,"cost_won":1266720,"prev_year_cost_won":1254220},{"year_month":"2026-01","usage_kwh":8699.031,"prev_year_usage_kwh":6928.798,"cost_won":1465320,"prev_year_cost_won":1470110},{"year_month":"2026-02","usage_kwh":5402.968,"prev_year_usage_kwh":6961.298,"cost_won":1528580,"prev_year_cost_won":1414410},{"year_month":"2026-03","usage_kwh":4104.6,"prev_year_usage_kwh":4119.212,"cost_won":925940,"prev_year_cost_won":999850},{"year_month":"2026-04","usage_kwh":2643.967,"prev_year_usage_kwh":2907.46,"cost_won":716830,"prev_year_cost_won":761020},{"year_month":"2026-05","usage_kwh":2712.216,"prev_year_usage_kwh":2541.278,"cost_won":629580,"prev_year_cost_won":617770},{"year_month":"2026-06","usage_kwh":1594.376,"prev_year_usage_kwh":3291.263,"cost_won":753240,"prev_year_cost_won":790790}]