[{"year_month":"2025-05","usage_kwh":56594.25,"prev_year_usage_kwh":24378.93,"cost_won":13494790,"prev_year_cost_won":8984050},{"year_month":"2025-06","usage_kwh":85702.05,"prev_year_usage_kwh":26044.11,"cost_won":15811430,"prev_year_cost_won":9337940},{"year_month":"2025-07","usage_kwh":92071.26,"prev_year_usage_kwh":30267.45,"cost_won":22890550,"prev_year_cost_won":10736960},{"year_month":"2025-08","usage_kwh":95885.91,"prev_year_usage_kwh":28330.92,"cost_won":22525220,"prev_year_cost_won":11134520},{"year_month":"2025-09","usage_kwh":110476.89,"prev_year_usage_kwh":25898.85,"cost_won":24291600,"prev_year_cost_won":10537880},{"year_month":"2025-10","usage_kwh":69423.12,"prev_year_usage_kwh":27389.79,"cost_won":20117730,"prev_year_cost_won":9097260},{"year_month":"2025-11","usage_kwh":44150.31,"prev_year_usage_kwh":39282.39,"cost_won":14982360,"prev_year_cost_won":10044040},{"year_month":"2025-12","usage_kwh":74990.34,"prev_year_usage_kwh":67920.48,"cost_won":14966720,"prev_year_cost_won":13680800},{"year_month":"2026-01","usage_kwh":95356.89,"prev_year_usage_kwh":79489.89,"cost_won":20421940,"prev_year_cost_won":21965760},{"year_month":"2026-02","usage_kwh":71058.87,"prev_year_usage_kwh":80401.41,"cost_won":23170340,"prev_year_cost_won":21357890},{"year_month":"2026-03","usage_kwh":62489.43,"prev_year_usage_kwh":67748.22,"cost_won":16975850,"prev_year_cost_won":18876620},{"year_month":"2026-04","usage_kwh":47746.53,"prev_year_usage_kwh":54169.11,"cost_won":14921830,"prev_year_cost_won":15554010},{"year_month":"2026-05","usage_kwh":63286.83,"prev_year_usage_kwh":56594.25,"cost_won":12827860,"prev_year_cost_won":13494790},{"year_month":"2026-06","usage_kwh":53077.14,"prev_year_usage_kwh":85702.05,"cost_won":15673390,"prev_year_cost_won":15811430}]