[{"reading_hour":"20260723 01:00","usage_kwh":1.56,"cost_won":206},{"reading_hour":"20260723 02:00","usage_kwh":1.55,"cost_won":204},{"reading_hour":"20260723 03:00","usage_kwh":1.61,"cost_won":212},{"reading_hour":"20260723 04:00","usage_kwh":1.61,"cost_won":213},{"reading_hour":"20260723 05:00","usage_kwh":1.66,"cost_won":220},{"reading_hour":"20260723 06:00","usage_kwh":1.68,"cost_won":222},{"reading_hour":"20260723 07:00","usage_kwh":1.54,"cost_won":203},{"reading_hour":"20260723 08:00","usage_kwh":1.52,"cost_won":200}]