[{"reading_hour":"20260723 01:00","usage_kwh":1.03,"cost_won":136},{"reading_hour":"20260723 02:00","usage_kwh":1.14,"cost_won":151},{"reading_hour":"20260723 03:00","usage_kwh":1.45,"cost_won":191},{"reading_hour":"20260723 04:00","usage_kwh":1.28,"cost_won":169},{"reading_hour":"20260723 05:00","usage_kwh":1.08,"cost_won":142},{"reading_hour":"20260723 06:00","usage_kwh":1.7,"cost_won":224},{"reading_hour":"20260723 07:00","usage_kwh":1.61,"cost_won":212},{"reading_hour":"20260723 08:00","usage_kwh":1.87,"cost_won":247}]